setup.py
scallopstogo/__init__.py
scallopstogo.egg-info/PKG-INFO
scallopstogo.egg-info/SOURCES.txt
scallopstogo.egg-info/dependency_links.txt
scallopstogo.egg-info/requires.txt
scallopstogo.egg-info/top_level.txt
scallopstogo/cal_format/__init__.py
scallopstogo/cal_format/cal_format.py
scallopstogo/cal_pull/__init__.py
scallopstogo/cal_pull/cal_pull.py
scallopstogo/cal_util/__init__.py
scallopstogo/cal_util/cal_util.py
scallopstogo/holidays/__init__.py
scallopstogo/holidays/holidays.py
scallopstogo/holidays/tests/__init__.py
scallopstogo/holidays/tests/test_holidays.py