Metadata-Version: 1.0
Name: scallopstogo
Version: 0.3.0
Summary: Python library of helper and connection functions for use with Google Calendar API
Home-page: UNKNOWN
Author: Andrew Lee
Author-email: andrewlee@indeed.com
License: Reserved
Platform: UNKNOWN
